{
 "msg1":{"msgA":"This msgA property value from Data Element 0 from folder publicMEANF", "msgB":"This msgB property value from Data Element 0 from folder publicMEANF"}, 
 "msg2":{"msgA":"This msgA property value from Data Element 1 from folder publicMEANF", "msgB":"This msgB property value from Data Element 1 from folder publicMEANF"}, 
 "msg3":{"msgA":"This mdgA property value from Data Element 2 from folder publicMEANF", "msgB":"This msgB property value from Data Element 2 from folder publicMEANF"}
}

